lisdk/__init__.py
lisdk/engines.py
lisdk/rsak.py
lisdk/rsam.py
lisdk/utils.py
lisdk-0.0.4.dist-info/licenses/LICENSE
lisdk-0.0.4.dist-info/METADATA
lisdk-0.0.4.dist-info/WHEEL
lisdk-0.0.4.dist-info/top_level.txt
lisdk-0.0.4.dist-info/RECORD
